dragon_player/__init__.py
dragon_player/cli.py
dragon_player/decorators.py
dragon_player/youtube_api.py
dragon_player-0.10.dist-info/METADATA
dragon_player-0.10.dist-info/WHEEL
dragon_player-0.10.dist-info/entry_points.txt
dragon_player-0.10.dist-info/top_level.txt
dragon_player-0.10.dist-info/RECORD
