Metadata-Version: 2.1
Name: dragon-player
Version: 0.10
Summary: The CLI YouTube Player
Home-page: https://github.com/pouya-eghbali/dragon
Author: Pouya Eghbali
Author-email: pouya.eghbali@yandex.ch
License: UNKNOWN
Platform: UNKNOWN
Requires-Dist: asciimatics
Requires-Dist: python-vlc
Requires-Dist: beautifulsoup4
Requires-Dist: requests
Requires-Dist: youtube-dl
